icsd/__init__.py
icsd/icsd3d.py
icsd/exporters/__init__.py
icsd/exporters/save.py
icsd/gridder/__init__.py
icsd/gridder/mkgrid.py
icsd/importers/__init__.py
icsd/importers/read.py
icsd/inversion/__init__.py
icsd/inversion/priorM0.py
icsd/inversion/regularize.py
icsd/inversion/solve.py
icsd/plotters/__init__.py
icsd/plotters/mpl_plot.py
icsd/plotters/pv_plot.py
tests/__init__.py
tests/test_icsd3d.py
tests/test_plot.py
icsd-0.1.0rc3.dist-info/LICENSE.md
icsd-0.1.0rc3.dist-info/METADATA
icsd-0.1.0rc3.dist-info/WHEEL
icsd-0.1.0rc3.dist-info/top_level.txt
icsd-0.1.0rc3.dist-info/zip-safe
icsd-0.1.0rc3.dist-info/RECORD
