Metadata-Version: 2.1
Name: icsd
Version: 0.1.0rc3
Summary: 'Inversion of current source density'
Author: 'Luca Peruzzo, Benjamin Mary'
Author-email: <benjamin.mary@unipd.it>
License: BSD 3-Clause License
Keywords: inversion,MALM
Classifier: Development Status :: 5 - Production/Stable
Classifier: Intended Audience :: Science/Research
Classifier: Intended Audience :: Developers
Classifier: Intended Audience :: Education
Classifier: License :: OSI Approved :: BSD License
Classifier: Natural Language :: English
Classifier: Operating System :: OS Independent
Classifier: Topic :: Scientific/Engineering
Classifier: Topic :: Software Development :: Libraries
Classifier: Programming Language :: Python :: 3 :: Only
Classifier: Programming Language :: Python :: 3.7
Classifier: Programming Language :: Python :: 3.8
Requires-Python: >=3.7
License-File: LICENSE.md
Requires-Dist: numpy (<1.23.0,>=1.16.5)
Requires-Dist: scipy
Requires-Dist: kneed
